testpilot/__init__.py
testpilot/__main__.py
testpilot/cli.py
testpilot/core.py
testpilot-0.2.9.dist-info/LICENSE
testpilot-0.2.9.dist-info/METADATA
testpilot-0.2.9.dist-info/WHEEL
testpilot-0.2.9.dist-info/entry_points.txt
testpilot-0.2.9.dist-info/top_level.txt
testpilot-0.2.9.dist-info/RECORD
