Metadata-Version: 2.2
Name: testpilot
Version: 0.2.9
Summary: Format, lint and test only the files that have changed on the current branch.
Home-page: https://github.com/hypothesis/testpilot
Project-URL: Bug Tracker, https://github.com/hypothesis/testpilot/issues
Project-URL: Changelog, https://github.com/hypothesis/testpilot/releases
Classifier: Programming Language :: Python :: 3
Classifier: License :: OSI Approved :: BSD License
Classifier: Intended Audience :: Developers
Requires-Python: >=3.9
License-File: LICENSE
Requires-Dist: toml
